Workbook

Sheet Project Overview
B2: INFOSYS LTD
B5: FINANCIAL ANALYSIS | FY2014–FY2025
B8: PROJECT PROFILE | E8: ANALYTICAL SCOPE
B9: Company | C9: Infosys Ltd | E9: • Profit & Loss analysis
B10: Industry | C10: IT Services / Technology | E10: • Balance Sheet analysis
B11: Analysis Period | C11: FY2014–FY2025 | E11: • Cash Flow analysis
B12: Currency | C12: ₹ Crore | E12: • Ratio calculations & interpretation
B13: Project Type | C13: Corporate Financial Analysis | E13: • Profitability analysis
B14: Primary Tool | C14: Microsoft Excel + ChatGPT (AI Assistant ) | E14: • Efficiency & Working Capital analysis
E15: • Liquidity & Solvency analysis
E16: • Investment & financial conclusion
B18: PROJECT OBJECTIVE
B19: To evaluate Infosys Ltd.'s long-term financial performance using its financial statements and ratio framework, with emphasis on profitability, operating efficiency, working capital, liquidity, solvency and shareholder returns.
B23: WORKFLOW & TECHNIQUES | E23: PROJECT DELIVERABLE
B24: ✓ Financial statement analysis | E24: • 12-year financial statement dataset
B25: ✓ Ratio calculation & trend analysis | E25: • Linked ratio calculations
B26: ✓ Profitability & margin analysis | E26: • Five-sheet analytical framework
B27: ✓ Efficiency & working capital analysis | E27: • Management-style dashboard
B28: ✓ Liquidity & solvency analysis | E28: • Investment & financial conclusion
B29: ✓ Excel-based dashboard & visualization | E29: • Portfolio-ready Excel workbook
B31: WORKBOOK STRUCTURE
B32: Name & Details | D32: Project identity, analyst profile and portfolio purpose
B33: OBJECTIVE & METHODOLOGY | D33: Existing objective/methodology worksheet
B34: Profit & Loss | D34: Historical profit & loss statement
B35: Cash Flow Statement | D35: Historical cash flow statement
B36: Balance sheet | D36: Historical balance sheet
B37: Ratios Cal & Analysis | D37: Ratio calculations and underlying analysis
B38: Dashboard | D38: Financial performance dashboard and charts
B39: Profitability Analysis | D39: Profitability ratio analysis
B40: Efficiency & Working Capital An | D40: Operating efficiency and working capital analysis
B41: Liquidity & Solvency Analysis | D41: Liquidity and capital structure analysis
B42: Investment & Financial Conclusi | D42: Investment and financial conclusion
B44: Prepared as a finance portfolio project • Original analysis and calculations retained • Presentation redesigned for professional use

Sheet Name & Details
B1: INFOSYS LTD — FINANCIAL ANALYSIS PROJECT
B2: IT Services | Financial Performance & Ratio Analysis | FY2014–FY2025
B4: PROJECT & CREATOR DETAILS
B6: Project | C6: Infosys Ltd — Financial Performance Analysis & Dashboard
B7: Industry | C7: IT Services / Technology Services
B8: Analysis Period | C8: FY2014–FY2025
B9: Reporting Unit | C9: ₹ Crores, unless otherwise stated
B10: Prepared By | C10: Ayush Nitin Jagtap
B11: Professional Focus | C11: AI - Integrated Finance | Accounting | Finance & Business Analysis | Financial Modeling
B12: Education | C12: B.Com (Business Administration) | M.Com (Advanced Accounting & Income Tax)
B15: PROJECT PURPOSE
B16: To evaluate Infosys’ long-term financial performance using the Profit & Loss Account, Balance Sheet and Cash Flow Statement, supported by ratio analysis, profitability analysis, efficiency and working-capital analysis, liquidity and solvency analysis, and dashboard-based presentation.
B20: TOOLS, SKILLS & ANALYTICAL TECHNIQUES
B21: • Microsoft Excel
B22: • Financial Statement Analysis
B23: • Ratio Analysis
B24: • Profitability Analysis
B25: • Liquidity & Solvency Analysis
B26: • Efficiency & Working Capital Analysis
B27: • Cash Flow Analysis
B28: • Financial Dashboard & Data Visualization
B29: • Formula-driven analysis & linked schedules
B31: PORTFOLIO & CONTACT DETAILS
B32: Location | C32: Pune, Maharashtra, India
B33: Email | C33: ayushjagtap1657@gmail.com
B34: Project Type | C34: Financial Analysis / Portfolio Project
B35: Workbook Scope | C35: Financial statements, ratio calculations, analytical schedules and dashboard presentation
B36: Original analytical work retained; this sheet documents the project and creator details for portfolio presentation.
B37: INFOSYS LTD | FINANCIAL ANALYSIS | FY2014–FY2025

Sheet OBJECTIVE & METHODOLOGY
B1: OBJECTIVE & METHODOLOGY
B2: Infosys Ltd | IT Services | FY2014–FY2025 | Financial Analysis & Dashboard Project
B3: 1 | PROJECT OBJECTIVE
B4: Primary Objective | C4: To evaluate Infosys Ltd.’s long-term financial performance and financial position across FY2014–FY2025 using the company’s Profit & Loss Account, Balance Sheet and Cash Flow Statement, and to translate the results into structured financial and ratio-based insights.
B5: Analytical Focus | C5: The project covers revenue and profit trends, operating performance, cash generation, working capital, liquidity, solvency/capital structure, asset efficiency and selected financial ratios.
B7: 2 | SCOPE OF ANALYSIS
B8: Financial Statements | C8: Profit & Loss; Cash Flow Statement; Balance Sheet. These form the primary financial statement base for the linked calculations and analysis schedules.
B9: Ratio & Performance Analysis | C9: Sales growth, operating performance, net profit margin, fixed-asset turnover, net working capital, debtor days, inventory days, creditor days and debt-to-total-capital, along with profitability, efficiency, liquidity and solvency analysis.
B10: Dashboard & Presentation | C10: A dashboard layer consolidates selected financial trends and analytical outputs into a management-style visual summary for easier interpretation.
B12: 3 | METHODOLOGY
B13: Step 01 — Financial Data | C13: Organise the FY2014–FY2025 financial statement figures in Excel and establish consistent year-wise reporting in ₹ crores.
B14: Step 02 — Formula Linkage | C14: Use Excel formulas and linked schedules to derive growth rates, margins, working-capital measures, turnover metrics and capital-structure ratios from the underlying statements.
B15: Step 03 — Ratio Analysis | C15: Group the calculated metrics into profitability, efficiency & working capital, liquidity & solvency, and broader financial-performance sections.
B16: Step 04 — Interpretation | C16: Review the direction and movement of the calculated metrics over the analysis period and connect the results to the relevant financial statement drivers.
B17: Step 05 — Visualisation | C17: Present selected trends and analytical outputs through charts and a financial dashboard for portfolio-ready communication.
B19: 4 | AI-ASSISTED WORKFLOW
B20: AI Assistant | C20: ChatGPT was used as an AI assistant during the project workflow for analytical support, structuring ideas, interpretation support and presentation guidance. The underlying workbook, calculations and final Excel implementation remain the project work product.
B21: Human Validation | C21: Financial figures, formulas, analysis logic and final presentation were reviewed and implemented in Excel. AI assistance is treated as a productivity and reasoning aid rather than a substitute for financial analysis.
B23: 5 | PROJECT DELIVERABLES
B24: • Financial statement analysis across FY2014–FY2025
B25: • Formula-driven ratio calculation schedule
B26: • Profitability analysis
B27: • Efficiency & working capital analysis
B28: • Liquidity & solvency analysis
B29: • Cash flow analysis
B30: • Interactive/visual financial dashboard
B31: • Investment & financial conclusion
B33: 6 | DATA & INTERPRETATION NOTE
B34: Source Basis | C34: The workbook uses the financial statement data and supporting schedules contained within the project. The analysis period is FY2014–FY2025 and figures are presented in ₹ crores unless otherwise stated.
B35: Service-Business Context | C35: Because Infosys operates as an IT services business, inventory-related measures have limited relevance in comparison with working-capital, receivables, payables, cash generation and asset-efficiency measures. The workbook reflects this context in its ratio analysis.
B36: Professional documentation of the existing Infosys financial analysis workbook — original calculations and analytical schedules retained.
B37: INFOSYS LTD | OBJECTIVE & METHODOLOGY | FY2014–FY2025

Sheet Profit & Loss
A1: Infosys LTD Finacial ststement 2014-2025
A3: Profit & Loss
A4: All figures in Cr.
B5: 41699 | C5: 42064 | D5: 42430 | E5: 42795 | F5: 43160 | G5: 43525 | H5: 43891 | I5: 44256 | J5: 44621 | K5: 44986 | L5: 45352 | M5: 45717 | N5: TTM
A6: Sales - | B6: 50133 | C6: 53319 | D6: 62441 | E6: 68484 | F6: 70522 | G6: 82675 | H6: 90791 | I6: 100472 | J6: 121641 | K6: 146767 | L6: 153670 | M6: 162990 | N6: 173173
A7: Sales Growth % | B7: 0.2424 | C7: 0.0636 | D7: 0.1711 | E7: 0.0968 | F7: 0.0298 | G7: 0.1723 | H7: 0.0982 | I7: 0.1066 | J7: 0.2107 | K7: 0.2066 | L7: 0.047 | M7: 0.0606
A8: Expenses (COGS) - | B8: 36743 | C8: 38436 | D8: 45362 | E8: 49880 | F8: 51700 | G8: 62505 | H8: 68524 | I8: 72583 | J8: 90150 | K8: 111637 | L8: 117245 | M8: 123754 | N8: 132187
A9: Manufacturing Cost % | B9: 0.07 | C9: 0.08 | D9: 0.1 | E9: 0.1 | F9: 0.11 | G9: 0.12 | H9: 0.12 | I9: 0.13 | J9: 0.17 | K9: 0.18 | L9: 0.18 | M9: 0.19
A10: Employee Cost % | B10: 0.58 | C10: 0.56 | D10: 0.55 | E10: 0.55 | F10: 0.55 | G10: 0.55 | H10: 0.56 | I10: 0.55 | J10: 0.53 | K10: 0.53 | L10: 0.54 | M10: 0.53
A11: Other Cost % | B11: 0.09 | C11: 0.08 | D11: 0.08 | E11: 0.08 | F11: 0.08 | G11: 0.09 | H11: 0.07 | I11: 0.04 | J11: 0.04 | K11: 0.05 | L11: 0.05 | M11: 0.04
A12: Operating Profit | B12: 13390 | C12: 14883 | D12: 17079 | E12: 18604 | F12: 18822 | G12: 20170 | H12: 22267 | I12: 27889 | J12: 31491 | K12: 35130 | L12: 36425 | M12: 39236 | N12: 40986
A13: OPM % | B13: 0.27 | C13: 0.28 | D13: 0.27 | E13: 0.27 | F13: 0.27 | G13: 0.24 | H13: 0.25 | I13: 0.28 | J13: 0.26 | K13: 0.24 | L13: 0.24 | M13: 0.24 | N13: 0.24
A14: Other Income - | B14: 2664 | C14: 3430 | D14: 3120 | E14: 3050 | F14: 3311 | G14: 2882 | H14: 2803 | I14: 2201 | J14: 2295 | K14: 2701 | L14: 4711 | M14: 3600 | N14: 3064
A15: Exceptional items | B15: 0 | C15: 14 | D15: 0 | E15: 238 | F15: 253 | G15: 170 | H15: 183 | I15: 74 | J15: 177 | K15: 148 | L15: 285 | M15: 291
A16: Other income normal | B16: 2664 | C16: 3416 | D16: 3120 | E16: 2812 | F16: 3058 | G16: 2712 | H16: 2620 | I16: 2127 | J16: 2118 | K16: 2553 | L16: 4426 | M16: 3309
A17: Interest | B17: 9 | C17: 12 | D17: 0 | E17: 0 | F17: 0 | G17: 0 | H17: 170 | I17: 195 | J17: 200 | K17: 284 | L17: 470 | M17: 416 | N17: 413
A18: Depreciation | B18: 1317 | C18: 1017 | D18: 1459 | E18: 1703 | F18: 1863 | G18: 2011 | H18: 2893 | I18: 3267 | J18: 3476 | K18: 4225 | L18: 4678 | M18: 4812 | N18: 4776
A19: Profit before tax | B19: 14728 | C19: 17284 | D19: 18740 | E19: 19951 | F19: 20270 | G19: 21041 | H19: 22007 | I19: 26628 | J19: 30110 | K19: 33322 | L19: 35988 | M19: 37608 | N19: 38861
A20: Tax % | B20: 0.28 | C20: 0.28 | D20: 0.28 | E20: 0.28 | F20: 0.21 | G20: 0.27 | H20: 0.24 | I20: 0.27 | J20: 0.26 | K20: 0.28 | L20: 0.27 | M20: 0.29
A21: Net Profit - | B21: 10656 | C21: 12372 | D21: 13489 | E21: 14353 | F21: 16029 | G21: 15410 | H21: 16639 | I21: 19423 | J21: 22146 | K21: 24108 | L21: 26248 | M21: 26750 | N21: 28003
A22: Profit from Associates | B22: 0 | C22: -1 | D22: 0 | E22: 0 | F22: 0 | G22: 0 | H22: 0 | I22: 0 | J22: 0 | K22: 0 | L22: 0 | M22: 0
A23: Minority share | B23: 0 | C23: 0 | D23: 0 | E23: 0 | F23: 0 | G23: -6 | H23: -45 | I23: -72 | J23: -36 | K23: -13 | L23: -15 | M23: -37
A24: Exceptional items AT | B24: 0 | C24: 10 | D24: 0 | E24: 171 | F24: 196 | G24: 124 | H24: 135 | I24: 54 | J24: 130 | K24: 107 | L24: 208 | M24: 197
A25: Profit excl Excep | B25: 10656 | C25: 12362 | D25: 13489 | E25: 14182 | F25: 15833 | G25: 15286 | H25: 16504 | I25: 19369 | J25: 22016 | K25: 24001 | L25: 26040 | M25: 26553
A26: Profit for PE | B26: 10656 | C26: 12362 | D26: 13489 | E26: 14182 | F26: 15833 | G26: 15280 | H26: 16459 | I26: 19297 | J26: 21980 | K26: 23988 | L26: 26025 | M26: 26516
A27: Profit for EPS | B27: 10656 | C27: 12372 | D27: 13489 | E27: 14353 | F27: 16029 | G27: 15404 | H27: 16594 | I27: 19351 | J27: 22110 | K27: 24095 | L27: 26233 | M27: 26713
A28: Profit Growth % | B28: 0.13 | C28: 0.16 | D28: 0.09 | E28: 0.05 | F28: 0.12 | G28: -0.03 | H28: 0.08 | I28: 0.17 | J28: 0.14 | K28: 0.09 | L28: 0.08 | M28: 0.02
A29: EPS in Rs | B29: 23.31 | C29: 26.93 | D29: 29.36 | E29: 31.24 | F29: 36.69 | G29: 35.26 | H29: 38.96 | I29: 45.42 | J29: 52.56 | K29: 58.08 | L29: 63.2 | M29: 64.32 | N29: 67.73
A30: Dividend Payout % | B30: 0.34 | C30: 0.55 | D30: 0.41 | E30: 0.41 | F30: 0.59 | G30: 0.6 | H30: 0.45 | I30: 0.59 | J30: 0.59 | K30: 0.58 | L30: 0.73 | M30: 0.67

Sheet Cash Flow Statement
A1: Infosys LTD Finacial ststement 2014-2025
A3: Cash Flows
A4: All Fifures in CR.
B5: 41699 | C5: 42064 | D5: 42430 | E5: 42795 | F5: 43160 | G5: 43525 | H5: 43891 | I5: 44256 | J5: 44621 | K5: 44986 | L5: 45352 | M5: 45717
A6: Cash from Operating Activity - | B6: 9825 | C6: 8353 | D6: 10028 | E6: 11531 | F6: 13218 | G6: 14841 | H6: 17003 | I6: 23224 | J6: 23885 | K6: 22467 | L6: 25210 | M6: 35694
A7: Profit from operations | B7: 14172 | C7: 15946 | D7: 17839 | E7: 19340 | F7: 19963 | G7: 22126 | H7: 23920 | I7: 28845 | J7: 32921 | K7: 37605 | L7: 39523 | M7: 41591
A8: Receivables | B8: -1406 | C8: -1475 | D8: -1654 | E8: -1743 | F8: -1523 | G8: -2881 | H8: -3861 | I8: -1835 | J8: -7937 | K8: -7076 | L8: -2667 | M8: -1769
A9: Payables | B9: 0 | C9: 0 | D9: 242 | E9: -19 | F9: 328 | G9: 916 | H9: -373 | I9: -245 | J9: 1489 | K9: -279 | L9: 91 | M9: 176
A10: Loans Advances | B10: -1060 | C10: -221 | D10: -1134 | E10: 0 | F10: 0 | G10: 0 | H10: 0 | I10: -534 | J10: -1914 | K10: -3108 | L10: -1172 | M10: -1024
A11: Other WC items | B11: 1993 | C11: 854 | D11: 600 | E11: -394 | F11: 1279 | G11: 1512 | H11: 1867 | I11: 3382 | J11: 6938 | K11: 4119 | L11: -1334 | M11: 2322
A12: Working capital changes | B12: -473 | C12: -842 | D12: -1946 | E12: -2156 | F12: 84 | G12: -453 | H12: -2367 | I12: 768 | J12: -1424 | K12: -6344 | L12: -5082 | M12: -295
A13: Direct taxes | B13: -3874 | C13: -6751 | D13: -5865 | E13: -5653 | F13: -6829 | G13: -6832 | H13: -4550 | I13: -6389 | J13: -7612 | K13: -8794 | L13: -9231 | M13: -5602
A14: Cash from Investing Activity - | B14: -2563 | C14: 999 | D14: -885 | E14: -14664 | F14: 4533 | G14: -632 | H14: -331 | I14: -7373 | J14: -6485 | K14: -1071 | L14: -5093 | M14: -1864
A15: Fixed assets purchased | B15: -2748 | C15: -2247 | D15: -2723 | E15: -2760 | F15: -1998 | G15: -2445 | H15: -3307 | I15: -2107 | J15: -2161 | K15: -2579 | L15: -2201 | M15: -2237
A16: Fixed assets sold | B16: 3 | C16: 0 | D16: 0 | E16: 0 | F16: 0 | G16: 0 | H16: 0 | I16: 0 | J16: 0 | K16: 0 | L16: 0 | M16: 0
A17: Investments purchased | B17: -25046 | C17: -23923 | D17: -24577 | E17: -66410 | F17: -69159 | G17: -79410 | H17: -37482 | I17: -46738 | J17: -59951 | K17: -75800 | L17: -78118 | M17: -82753
... A30: Net Cash Flow | B30: 4118 | C30: 4417 | D30: 2330 | E30: -10072 | F30: -2754 | G30: -303 | H30: -919 | I30: 6065 | J30: -7242 | K30: -5299 | L30: 2613 | M30: 9669

Sheet Balance sheet
A1: Infosys LTD Finacial ststement 2014-2025
A3: Balance Sheet
A4: All figures in Cr
B5: 41699 | C5: 42064 | D5: 42430 | E5: 42795 | F5: 43160 | G5: 43525 | H5: 43891 | I5: 44256 | J5: 44621 | K5: 44986 | L5: 45352 | M5: 45717 | N5: 45901
A6: Equity Capital | B6: 286 | C6: 572 | D6: 1144 | E6: 1144 | F6: 1088 | G6: 2170 | H6: 2122 | I6: 2124 | J6: 2098 | K6: 2069 | L6: 2071 | M6: 2073 | N6: 2074
A7: Reserves | B7: 44244 | C7: 50164 | D7: 60600 | E7: 67838 | F7: 63835 | G7: 62778 | H7: 63328 | I7: 74227 | J7: 73252 | K7: 73338 | L7: 86045 | M7: 93745 | N7: 101256
A8: Borrowings - | B8: 0 | C8: 0 | D8: 0 | E8: 0 | F8: 0 | G8: 0 | H8: 4633 | I8: 5325 | J8: 5474 | K8: 8299 | L8: 8359 | M8: 8227 | N8: 8755
A9: Lease Liabilities | B9: 0 | C9: 0 | D9: 0 | E9: 0 | F9: 0 | G9: 0 | H9: 4633 | I9: 5325 | J9: 5474 | K9: 8299 | L9: 8359 | M9: 8227 | N9: 8755
A10: Other Liabilities - | B10: 12436 | C10: 15553 | D10: 13354 | E10: 14166 | F10: 14426 | G10: 19118 | H10: 21717 | I10: 25835 | J10: 35905 | K10: 40890 | L10: 40885 | M10: 43750 | N10: 48295
A11: Non controlling int | B11: 0 | C11: 0 | D11: 0 | E11: 0 | F11: 1 | G11: 58 | H11: 394 | I11: 431 | J11: 386 | K11: 388 | L11: 345 | M11: 385 | N11: 414
A12: Trade Payables | B12: 173 | C12: 140 | D12: 386 | E12: 367 | F12: 694 | G12: 1655 | H12: 2852 | I12: 2645 | J12: 4134 | K12: 3865 | L12: 3956 | M12: 4164 | N12: 3839
A13: Advance from Customers | B13: 40 | C13: 27 | D13: 28 | E13: 0 | F13: 0 | G13: 0 | H13: 0 | I13: 0 | J13: 0 | K13: 0 | L13: 0 | M13: 0
A14: Other liability items | B14: 12223 | C14: 15386 | D14: 12940 | E14: 13799 | F14: 13731 | G14: 17405 | H14: 18471 | I14: 22759 | J14: 31385 | K14: 36637 | L14: 36584 | M14: 39201 | N14: 44042
A15: Total Liabilities | B15: 56966 | C15: 66289 | D15: 75098 | E15: 83148 | F15: 79349 | G15: 84066 | H15: 91800 | I15: 107511 | J15: 116729 | K15: 124596 | L15: 137360 | M15: 147795 | N15: 160380
A16: Fixed Assets - | B16: 8378 | C16: 11346 | D16: 13386 | E16: 14179 | F16: 12574 | G16: 15710 | H16: 23789 | I16: 25505 | J16: 25800 | K16: 29225 | L16: 27622 | M16: 30961 | N16: 32656
A17: Land | B17: 1142 | C17: 1564 | D17: 1622 | E17: 1095 | F17: 1229 | G17: 1307 | H17: 1950 | I17: 2036 | J17: 2065 | K17: 2054 | L17: 2037 | M17: 2079
A18: Building | B18: 5238 | C18: 6102 | D18: 6325 | E18: 8419 | F18: 9334 | G18: 10270 | H18: 15104 | I18: 16328 | J18: 16761 | K18: 16903 | L18: 16515 | M18: 16376
A19: Plant Machinery | B19: 1150 | C19: 1427 | D19: 1759 | E19: 2048 | F19: 2306 | G19: 2709 | H19: 3185 | I19: 3296 | J19: 3210 | K19: 3302 | L19: 3428 | M19: 3461
A20: Equipments | B20: 551 | C20: 676 | D20: 839 | E20: 922 | F20: 1002 | G20: 1101 | H20: 1265 | I20: 1371 | J20: 1427 | K20: 1482 | L20: 1528 | M20: 1628
A21: Computers | B21: 2659 | C21: 3347 | D21: 4486 | E21: 4945 | F21: 4903 | G21: 6287 | H21: 7423 | I21: 8650 | J21: 9936 | K21: 11898 | L21: 12353 | M21: 12925
A22: Furniture n fittings | B22: 805 | C22: 958 | D22: 1444 | E22: 1277 | F22: 1393 | G22: 1620 | H22: 2073 | I22: 2149 | J22: 2279 | K22: 2303 | L22: 2326 | M22: 2340
A23: Vehicles | B23: 35 | C23: 34 | D23: 29 | E23: 31 | F23: 31 | G23: 38 | H23: 69 | I23: 74 | J23: 71 | K23: 60 | L23: 62 | M23: 72
A24: Intangible Assets | B24: 2244 | C24: 3637 | D24: 3858 | E24: 3743 | F24: 2237 | G24: 3640 | H24: 5527 | I24: 6372 | J24: 6495 | K24: 7594 | L24: 7653 | M24: 10626 | N24: 14670
A25: Other fixed assets | B25: 126 | C25: 71 | D25: 931 | E25: 899 | F25: 545 | G25: 1093 | H25: 2289 | I25: 2730 | J25: 2766 | K25: 3281 | L25: 3294 | M25: 5184
A26: Gross Block | B26: 13950 | C26: 17816 | D26: 21293 | E26: 23379 | F26: 22980 | G26: 28065 | H26: 38885 | I26: 43006 | J26: 45010 | K26: 48877 | L26: 49196 | M26: 54691
A27: Accumulated Depreciation | B27: 5572 | C27: 6470 | D27: 7907 | E27: 9200 | F27: 10406 | G27: 12355 | H27: 15096 | I27: 17501 | J27: 19210 | K27: 19652 | L27: 21574 | M27: 23730
A28: CWIP | B28: 961 | C28: 776 | D28: 960 | E28: 1365 | F28: 1606 | G28: 1388 | H28: 954 | I28: 922 | J28: 416 | K28: 288 | L28: 293 | M28: 814 | N28: 1124
A29: Investments | B29: 4331 | C29: 2270 | D29: 1892 | E29: 16423 | F29: 12163 | G29: 11261 | H29: 8792 | I29: 14205 | J29: 20324 | K29: 19478 | L29: 24623 | M29: 23541 | N29: 23485
A30: Other Assets - | B30: 43296 | C30: 51897 | D30: 58860 | E30: 51181 | F30: 53006 | G30: 55707 | H30: 58265 | I30: 66879 | J30: 70189 | K30: 75605 | L30: 84822 | M30: 92479 | N30: 103115
A31: Trade receivables | B31: 8351 | C31: 9713 | D31: 11330 | E31: 12322 | F31: 13142 | G31: 14827 | H31: 18487 | I31: 19294 | J31: 22698 | K31: 25424 | L31: 30193 | M31: 31158 | N31: 33968
A32: Cash Equivalents | B32: 25950 | C32: 30367 | D32: 32697 | E32: 22625 | F32: 19818 | G32: 19568 | H32: 18649 | I32: 24714 | J32: 17472 | K32: 12173 | L32: 14786 | M32: 24455 | N32: 31832
A33: Loans n Advances | B33: 1484 | C33: 399 | D33: 614 | E33: 844 | F33: 830 | G33: 1524 | H33: 1359 | I33: 1460 | J33: 2491 | K33: 3242 | L33: 10330 | M33: 6717 | N33: 4021
A34: Other asset items | B34: 7511 | C34: 11418 | D34: 14219 | E34: 15390 | F34: 19216 | G34: 19788 | H34: 19770 | I34: 21411 | J34: 27528 | K34: 34766 | L34: 29513 | M34: 30149 | N34: 33294
A35: Total Assets | B35: 56966 | C35: 66289 | D35: 75098 | E35: 83148 | F35: 79349 | G35: 84066 | H35: 91800 | I35: 107511 | J35: 116729 | K35: 124596 | L35: 137360 | M35: 147795 | N35: 160380

Sheet Ratios Cal & Analysis
A1: Ratios Calculation & Analysis Infosys Ltd
A3: No. | B3: Particular | C3: 41699 | D3: 42064 | E3: 42430 | F3: 42795 | G3: 43160 | H3: 43525 | I3: 43891 | J3: 44256 | K3: 44621 | L3: 44986 | M3: 45352 | N3: 45717
A4: 1 | B4: Profit & Loss
A5: - | B5: Sales Growth (CY sales/PY Sales-1) | D5: ='Profit & Loss'!C6/'Profit & Loss'!B6-1 -> 0.063550954 | E5: ='Profit & Loss'!D6/'Profit & Loss'!C6-1 -> 0.17108348 | F5: ='Profit & Loss'!E6/'Profit & Loss'!D6-1 -> 0.09677936 | G5: ='Profit & Loss'!F6/'Profit & Loss'!E6-1 -> 0.029758776 | H5: ='Profit & Loss'!G6/'Profit & Loss'!F6-1 -> 0.1723292 | I5: ='Profit & Loss'!H6/'Profit & Loss'!G6-1 -> 0.098167523 | J5: ='Profit & Loss'!I6/'Profit & Loss'!H6-1 -> 0.10662951 | K5: ='Profit & Loss'!J6/'Profit & Loss'!I6-1 -> 0.21069552 | ... N5: ='Profit & Loss'!M6/'Profit & Loss'!L6-1 -> 0.060649444
A6: - | B6: Operating Performance Management | C6: ='Profit & Loss'!B13 -> 0.27 | D6: ='Profit & Loss'!C13 -> 0.28 | E6: ='Profit & Loss'!D13 -> 0.27 | F6: ='Profit & Loss'!E13 -> 0.27 | G6: ='Profit & Loss'!F13 -> 0.27 | H6: ='Profit & Loss'!G13 -> 0.24 | I6: ='Profit & Loss'!H13 -> 0.25 | J6: ='Profit & Loss'!I13 -> 0.28 | ... N6: ='Profit & Loss'!M13 -> 0.24 | P6: Performing consistently average of | R6: =AVERAGE(C6:N6) -> 0.25916667
A7: - | B7: Net Profit Margin (NP/Sales) | C7: ='Profit & Loss'!B21/'Profit & Loss'!B6 -> 0.2125546 | D7: ='Profit & Loss'!C21/'Profit & Loss'!C6 -> 0.23203736 | E7: ='Profit & Loss'!D21/'Profit & Loss'!D6 -> 0.21602793 | F7: ='Profit & Loss'!E21/'Profit & Loss'!E6 -> 0.2095818 | G7: ='Profit & Loss'!F21/'Profit & Loss'!F6 -> 0.22729077 | H7: ='Profit & Loss'!G21/'Profit & Loss'!G6 -> 0.1863925 | I7: ='Profit & Loss'!H21/'Profit & Loss'!H6 -> 0.18326706 | J7: ='Profit & Loss'!I21/'Profit & Loss'!I6 -> 0.19331754 | ... N7: ='Profit & Loss'!M21/'Profit & Loss'!M6 -> 0.1641205 | P7: Net profit margins declined after FY2019 due to margin pressures
A9: 2 | B9: Balance sheet
A10: - | B10: Fixed assets turnover ratio (Sales/Net fixed assets) | C10: ='Profit & Loss'!B6/'Balance sheet'!B16/100 -> 0.059838864 | D10: ='Profit & Loss'!C6/'Balance sheet'!C16/100 -> 0.046993654 | E10: ='Profit & Loss'!D6/'Balance sheet'!D16/100 -> 0.046646496 | F10: ='Profit & Loss'!E6/'Balance sheet'!E16/100 -> 0.048299598 | G10: ='Profit & Loss'!F6/'Balance sheet'!F16/100 -> 0.056085573 | H10: ='Profit & Loss'!G6/'Balance sheet'!G16/100 -> 0.052625716 | I10: ='Profit & Loss'!H6/'Balance sheet'!H16/100 -> 0.038165118 | J10: ='Profit & Loss'!I6/'Balance sheet'!I16/100 -> 0.03939306 | ... N10: ='Profit & Loss'!M6/'Balance sheet'!M16/100 -> 0.052643648 | P10: The average return of fixed assets are | R10: =AVERAGE(C10:N10) -> 0.049474356
A11: - | B11: Net working capital (Current assets-Current Liabilities) | C11: ='Balance sheet'!B31+'Balance sheet'!B32+'Balance sheet'!B33+'Balance sheet'!B34-'Balance sheet'!B12+'Balance sheet'!B13+'Balance sheet'!B14 -> 55386 | D11: ='Balance sheet'!C31+'Balance sheet'!C32+'Balance sheet'!C33+'Balance sheet'!C34-'Balance sheet'!C12+'Balance sheet'!C13+'Balance sheet'!C14 -> 67170 | E11: ='Balance sheet'!D31+'Balance sheet'!D32+'Balance sheet'!D33+'Balance sheet'!D34-'Balance sheet'!D12+'Balance sheet'!D13+'Balance sheet'!D14 -> 71442 | F11: ='Balance sheet'!E31+'Balance sheet'!E32+'Balance sheet'!E33+'Balance sheet'!E34-'Balance sheet'!E12+'Balance sheet'!E13+'Balance sheet'!E14 -> 64613 | G11: ='Balance sheet'!F31+'Balance sheet'!F32+'Balance sheet'!F33+'Balance sheet'!F34-'Balance sheet'!F12+'Balance sheet'!F13+'Balance sheet'!F14 -> 66043 | H11: ='Balance sheet'!G31+'Balance sheet'!G32+'Balance sheet'!G33+'Balance sheet'!G34-'Balance sheet'!G12+'Balance sheet'!G13+'Balance sheet'!G14 -> 71457 | I11: ='Balance sheet'!H31+'Balance sheet'!H32+'Balance sheet'!H33+'Balance sheet'!H34-'Balance sheet'!H12+'Balance sheet'!H13+'Balance sheet'!H14 -> 73884 | J11: ='Balance sheet'!I31+'Balance sheet'!I32+'Balance sheet'!I33+'Balance sheet'!I34-'Balance sheet'!I12+'Balance sheet'!I13+'Balance sheet'!I14 -> 86993 | ... M11: ='Balance sheet'!L31+'Balance sheet'!L32+'Balance sheet'!L33+'Balance sheet'!L34-'Balance sheet'!L12+'Balance sheet'!L13+'Balance sheet'!L14 -> 117450 | N11: =('Balance sheet'!M31+'Balance sheet'!M32+'Balance sheet'!M33+'Balance sheet'!M34)-('Balance sheet'!M12+'Balance sheet'!M13+'Balance sheet'!M14) -> 49114
A12: - | B12: Debtor days (Average Trade Receivables /Revenue X 365) in Days | C12: =AVERAGE('Balance sheet'!A31,'Balance sheet'!B31)/'Balance sheet'!B7*365 -> 68.893296 | D12: =AVERAGE('Balance sheet'!B31,'Balance sheet'!C31)/'Balance sheet'!C7*365 -> 65.718045 | E12: =AVERAGE('Balance sheet'!C31,'Balance sheet'!D31)/'Balance sheet'!D7*365 -> 63.372071 | F12: =AVERAGE('Balance sheet'!D31,'Balance sheet'!E31)/'Balance sheet'!E7*365 -> 63.629382 | G12: =AVERAGE('Balance sheet'!E31,'Balance sheet'!F31)/'Balance sheet'!F7*365 -> 72.799875 | H12: =AVERAGE('Balance sheet'!F31,'Balance sheet'!G31)/'Balance sheet'!G7*365 -> 81.307823 | I12: =AVERAGE('Balance sheet'!G31,'Balance sheet'!H31)/'Balance sheet'!H7*365 -> 96.005006 | J12: =AVERAGE('Balance sheet'!H31,'Balance sheet'!I31)/'Balance sheet'!I7*365 -> 92.891165 | ... N12: =AVERAGE('Balance sheet'!L31,'Balance sheet'!M31)/'Balance sheet'!M7*365 -> 119.43632
A13: - | B13: Inventory days (Average inventory/COGS X 365 ) | C13: Inventory days not significant due to service-based business model Not applicable (service-based business)
A14: - | B14: Creditor days (Average trade payable/COGS X 365) In Days | C14: =AVERAGE('Balance sheet'!A12,'Balance sheet'!B12)/'Profit & Loss'!B8*365 -> 1.7185586 | D14: =AVERAGE('Balance sheet'!B12,'Balance sheet'!C12)/'Profit & Loss'!C8*365 -> 1.4861718 | E14: =AVERAGE('Balance sheet'!C12,'Balance sheet'!D12)/'Profit & Loss'!D8*365 -> 2.1161986 | F14: =AVERAGE('Balance sheet'!D12,'Balance sheet'!E12)/'Profit & Loss'!E8*365 -> 2.7550621 | G14: =AVERAGE('Balance sheet'!E12,'Balance sheet'!F12)/'Profit & Loss'!F8*365 -> 3.7453095 | H14: =AVERAGE('Balance sheet'!F12,'Balance sheet'!G12)/'Profit & Loss'!G8*365 -> 6.8585313 | I14: =AVERAGE('Balance sheet'!G12,'Balance sheet'!H12)/'Profit & Loss'!H8*365 -> 12.003495 | J14: =AVERAGE('Balance sheet'!H12,'Balance sheet'!I12)/'Profit & Loss'!I8*365 -> 13.821453 | ... N14: =AVERAGE('Balance sheet'!L12,'Balance sheet'!M12)/'Profit & Loss'!M8*365 -> 11.974562
A15: - | B15: Debt to total capital (Debt/(Debt+Reserves+Share Capital) | C15: ='Balance sheet'!B8/('Balance sheet'!B8+SUM('Balance sheet'!B6:B7)) -> 0 | D15: ='Balance sheet'!C8/('Balance sheet'!C8+SUM('Balance sheet'!C6:C7)) -> 0 | E15: ='Balance sheet'!D8/('Balance sheet'!D8+SUM('Balance sheet'!D6:D7)) -> 0 | F15: ='Balance sheet'!E8/('Balance sheet'!E8+SUM('Balance sheet'!E6:E7)) -> 0 | G15: ='Balance sheet'!F8/('Balance sheet'!F8+SUM('Balance sheet'!F6:F7)) -> 0 | H15: ='Balance sheet'!G8/('Balance sheet'!G8+SUM('Balance sheet'!G6:G7)) -> 0 | I15: ='Balance sheet'!H8/('Balance sheet'!H8+SUM('Balance sheet'!H6:H7)) -> 0.06610733 | J15: ='Balance sheet'!I8/('Balance sheet'!I8+SUM('Balance sheet'!I6:I7)) -> 0.065196631 | ... N15: ='Balance sheet'!M8/('Balance sheet'!M8+SUM('Balance sheet'!M6:M7)) -> 0.079071556
A18: 3 | B18: Cash Flow Statement Analysis
A19: - | B19: Cashflow from Operations | C19: ='Cash Flow Statement'!B6 -> 9825 | D19: ='Cash Flow Statement'!C6 -> 8353 | E19: ='Cash Flow Statement'!D6 -> 10028 | F19: ='Cash Flow Statement'!E6 -> 11531 | G19: ='Cash Flow Statement'!F6 -> 13218 | H19: ='Cash Flow Statement'!G6 -> 14841 | I19: ='Cash Flow Statement'!H6 -> 17003 | J19: ='Cash Flow Statement'!I6 -> 23224 | ... N19: ='Cash Flow Statement'!M6 -> 35694 | P19: Cash flows from operations consistently exceeded net profit, demonstrating high earnings quality and strong cash conversion. This indicates that reported profits are supported by actual cash generation.
A20: - | B20: Net Profit | C20: ='Profit & Loss'!B21 -> 10656 | D20: ='Profit & Loss'!C21 -> 12372 | E20: ='Profit & Loss'!D21 -> 13489 | F20: ='Profit & Loss'!E21 -> 14353 | G20: ='Profit & Loss'!F21 -> 16029 | H20: ='Profit & Loss'!G21 -> 15410 | I20: ='Profit & Loss'!H21 -> 16639 | J20: ='Profit & Loss'!I21 -> 19423 | ... N20: ='Profit & Loss'!M21 -> 26750
A21: - | B21: Cashflow from Investing | C21: ='Cash Flow Statement'!B7 -> 14172 | D21: ='Cash Flow Statement'!C7 -> 15946 | E21: ='Cash Flow Statement'!D7 -> 17839 | F21: ='Cash Flow Statement'!E7 -> 19340 | G21: ='Cash Flow Statement'!F7 -> 19963 | H21: ='Cash Flow Statement'!G7 -> 22126 | I21: ='Cash Flow Statement'!H7 -> 23920 | J21: ='Cash Flow Statement'!I7 -> 28845 | ... N21: ='Cash Flow Statement'!M7 -> 41591
A22: - | B22: Cashflow from Financing | C22: ='Cash Flow Statement'!B8 -> -1406 | D22: ='Cash Flow Statement'!C8 -> -1475 | E22: ='Cash Flow Statement'!D8 -> -1654 | F22: ='Cash Flow Statement'!E8 -> -1743 | G22: ='Cash Flow Statement'!F8 -> -1523 | H22: ='Cash Flow Statement'!G8 -> -2881 | I22: ='Cash Flow Statement'!H8 -> -3861 | J22: ='Cash Flow Statement'!I8 -> -1835 | ... N22: ='Cash Flow Statement'!M8 -> -1769
A23: - | B23: Cumulative Cashflow from operations | C23: ='Cash Flow Statement'!B9 -> 0 | D23: ='Cash Flow Statement'!C9 -> 0 | E23: ='Cash Flow Statement'!D9 -> 242 | F23: ='Cash Flow Statement'!E9 -> -19 | G23: ='Cash Flow Statement'!F9 -> 328 | H23: ='Cash Flow Statement'!G9 -> 916 | I23: ='Cash Flow Statement'!H9 -> -373 | J23: ='Cash Flow Statement'!I9 -> -245 | ... N23: ='Cash Flow Statement'!M9 -> 176
A24: - | B24: Cumulative Net Profit | C24: 10656 | D24: 23028 | E24: 36517 | F24: 50870 | G24: 66899 | H24: 82309 | I24: 98948 | J24: 118371 | K24: 140517 | L24: 164625 | M24: 190873 | N24: 217623
B27: Return on Capital Employed Operating Profit(EBIT) / Total Assets - Current Liablities X 100 | C27: ='Profit & Loss'!B12/('Balance sheet'!B35-SUM('Balance sheet'!B12,'Balance sheet'!B10,'Balance sheet'!B8)) -> 0.30186893 | D27: ='Profit & Loss'!C12/('Balance sheet'!C35-SUM('Balance sheet'!C12,'Balance sheet'!C10,'Balance sheet'!C8)) -> 0.29415369 | E27: ='Profit & Loss'!D12/('Balance sheet'!D35-SUM('Balance sheet'!D12,'Balance sheet'!D10,'Balance sheet'!D8)) -> 0.27835001 | F27: ='Profit & Loss'!E12/('Balance sheet'!E35-SUM('Balance sheet'!E12,'Balance sheet'!E10,'Balance sheet'!E8)) -> 0.27113605 | G27: ='Profit & Loss'!F12/('Balance sheet'!F35-SUM('Balance sheet'!F12,'Balance sheet'!F10,'Balance sheet'!F8)) -> 0.2930452 | H27: ='Profit & Loss'!G12/('Balance sheet'!G35-SUM('Balance sheet'!G12,'Balance sheet'!G10,'Balance sheet'!G8)) -> 0.31867663 | I27: ='Profit & Loss'!H12/('Balance sheet'!H35-SUM('Balance sheet'!H12,'Balance sheet'!H10,'Balance sheet'!H8)) -> 0.35571424 | J27: ='Profit & Loss'!I12/('Balance sheet'!I35-SUM('Balance sheet'!I12,'Balance sheet'!I10,'Balance sheet'!I8)) -> 0.37838168 | ... N27: ='Profit & Loss'!M12/('Balance sheet'!M35-SUM('Balance sheet'!M12,'Balance sheet'!M10,'Balance sheet'!M8)) -> 0.42808824
B28: Return on Equity % | C28: ='Profit & Loss'!B21/SUM('Balance sheet'!B6:B7) -> 0.23929935 | D28: ='Profit & Loss'!C21/SUM('Balance sheet'!C6:C7) -> 0.24385052 | E28: ='Profit & Loss'!D21/SUM('Balance sheet'!D6:D7) -> 0.21846657 | F28: ='Profit & Loss'!E21/SUM('Balance sheet'!E6:E7) -> 0.20806877 | G28: ='Profit & Loss'!F21/SUM('Balance sheet'!F6:F7) -> 0.24689247 | H28: ='Profit & Loss'!G21/SUM('Balance sheet'!G6:G7) -> 0.23726674 | I28: ='Profit & Loss'!H21/SUM('Balance sheet'!H6:H7) -> 0.2542246 | J28: ='Profit & Loss'!I21/SUM('Balance sheet'!I6:I7) -> 0.25439091 | ... N28: ='Profit & Loss'!M21/SUM('Balance sheet'!M6:M7) -> 0.2791751
B30: COGS for service-based company has been proxied using operating expenses wherever required. | I30: All monetary figures are in ₹ Crores unless stated otherwise.

Sheet Dashboard
A1: Infosys Ltd - Financial Performance Dashboard
A2: Period: 2014 - 2025 | Currency: Crores
A3: Capital-light IT services company with strong cash generation and conservative leverage
B5: Revenue | F5: Net Profit | J5: ROE | N5: ROCE | R5: Debt to Capital
B6: 1,62,990 Crores | F6: 26,750 Crores | J6: 0.28 | N6: 0.43 | R6: 0.079

Sheet Profitability Analysis
A1: Company Overview
A2: Company: Infosys Ltd
A3: Industry: IT Services
A4: Period Analysed: Mar-2014 to Mar-2025
A5: Objective: To evaluate profitability, efficiency, liquidity and capital structure using ratio analysis.
A6: Data Source: Audited Profit & Loss Account, Balance Sheet and Cash Flow Statements.
A13: Profitability Analysis
A15: No. | B15: Particular | C15: ='Ratios Cal & Analysis'!C3 -> 41699 | D15: ='Ratios Cal & Analysis'!D3 -> 42064 | E15: ='Ratios Cal & Analysis'!E3 -> 42430 | F15: ='Ratios Cal & Analysis'!F3 -> 42795 | G15: ='Ratios Cal & Analysis'!G3 -> 43160 | H15: ='Ratios Cal & Analysis'!H3 -> 43525 | I15: ='Ratios Cal & Analysis'!I3 -> 43891 | J15: ='Ratios Cal & Analysis'!J3 -> 44256 | ... N15: ='Ratios Cal & Analysis'!N3 -> 45717
A16: 1 | B16: {='Ratios Cal & Analysis'!B5:N5} -> Sales Growth (CY sales/PY Sales-1) | C16: 0 | D16: 0.063550954 | E16: 0.17108348 | F16: 0.09677936 | G16: 0.029758776 | H16: 0.1723292 | I16: 0.098167523 | J16: 0.10662951 | K16: 0.21069552 | L16: 0.20655864 | M16: 0.047033734 | N16: 0.060649444 | O16: #N/A
A17: 2 | B17: {='Ratios Cal & Analysis'!B6:N6} -> Operating Performance Management | C17: 0.27 | D17: 0.28 | E17: 0.27 | F17: 0.27 | G17: 0.27 | H17: 0.24 | I17: 0.25 | J17: 0.28 | K17: 0.26 | L17: 0.24 | M17: 0.24 | N17: 0.24 | O17: #N/A
A18: 3 | B18: {='Ratios Cal & Analysis'!B7:N7} -> Net Profit Margin (NP/Sales) | C18: 0.2125546 | D18: 0.23203736 | E18: 0.21602793 | F18: 0.2095818 | G18: 0.22729077 | H18: 0.1863925 | I18: 0.18326706 | J18: 0.19331754 | K18: 0.18206033 | L18: 0.16426036 | M18: 0.17080757 | N18: 0.1641205 | O18: #N/A
A19: 4 | B19: {='Ratios Cal & Analysis'!B27:N28} -> Return on Capital Employed Operating Profit(EBIT) / Total Assets - Current Liablities X 100 | C19: 0.30186893 | D19: 0.29415369 | E19: 0.27835001 | F19: 0.27113605 | G19: 0.2930452 | H19: 0.31867663 | I19: 0.35571424 | J19: 0.37838168 | K19: 0.44218996 | L19: 0.49104023 | M19: 0.43280656 | N19: 0.42808824 | O19: #N/A
A20: 5 | B20: Return on Equity % | C20: 0.23929935 | D20: 0.24385052 | E20: 0.21846657 | F20: 0.20806877 | G20: 0.24689247 | H20: 0.23726674 | I20: 0.2542246 | J20: 0.25439091 | K20: 0.29390843 | L20: 0.31970507 | M20: 0.29788007 | N20: 0.2791751 | O20: #N/A

Sheet Efficiency & Working Capital An
A1: Company Overview
A2: Company: Infosys Ltd
A3: Industry: IT Services
A4: Period Analysed: Mar-2014 to Mar-2025
A5: Objective: To evaluate profitability, efficiency, liquidity and capital structure using ratio analysis.
A6: Data Source: Audited Profit & Loss Account, Balance Sheet and Cash Flow Statements.
A9: Efficiency & Working Capital Analysis
A11: No. | B11: Particular | C11: ='Ratios Cal & Analysis'!C3 -> 41699 | D11: ='Ratios Cal & Analysis'!D3 -> 42064 | E11: ='Ratios Cal & Analysis'!E3 -> 42430 | F11: ='Ratios Cal & Analysis'!F3 -> 42795 | G11: ='Ratios Cal & Analysis'!G3 -> 43160 | H11: ='Ratios Cal & Analysis'!H3 -> 43525 | I11: ='Ratios Cal & Analysis'!I3 -> 43891 | J11: ='Ratios Cal & Analysis'!J3 -> 44256 | ... N11: ='Ratios Cal & Analysis'!N3 -> 45717
A12: 1 | B12: Debtor days | C12: ='Ratios Cal & Analysis'!C12 -> 68.893296 | D12: ='Ratios Cal & Analysis'!D12 -> 65.718045 | E12: ='Ratios Cal & Analysis'!E12 -> 63.372071 | F12: ='Ratios Cal & Analysis'!F12 -> 63.629382 | G12: ='Ratios Cal & Analysis'!G12 -> 72.799875 | H12: ='Ratios Cal & Analysis'!H12 -> 81.307823 | I12: ='Ratios Cal & Analysis'!I12 -> 96.005006 | J12: ='Ratios Cal & Analysis'!J12 -> 92.891165 | ... N12: ='Ratios Cal & Analysis'!N12 -> 119.43632
A13: 2 | B13: Creditor days | C13: ='Ratios Cal & Analysis'!C14 -> 1.7185586 | D13: ='Ratios Cal & Analysis'!D14 -> 1.4861718 | E13: ='Ratios Cal & Analysis'!E14 -> 2.1161986 | F13: ='Ratios Cal & Analysis'!F14 -> 2.7550621 | G13: ='Ratios Cal & Analysis'!G14 -> 3.7453095 | H13: ='Ratios Cal & Analysis'!H14 -> 6.8585313 | I13: ='Ratios Cal & Analysis'!I14 -> 12.003495 | J13: ='Ratios Cal & Analysis'!J14 -> 13.821453 | ... N13: ='Ratios Cal & Analysis'!N14 -> 11.974562
A14: 3 | B14: Inventory Days | C14: Inventory days not significant due to service-based business model Not applicable (service-based business)
A15: 4 | B15: Fixed Asset Turnover Ratio | C15: ='Ratios Cal & Analysis'!C10 -> 0.059838864 | D15: ='Ratios Cal & Analysis'!D10 -> 0.046993654 | E15: ='Ratios Cal & Analysis'!E10 -> 0.046646496 | F15: ='Ratios Cal & Analysis'!F10 -> 0.048299598 | G15: ='Ratios Cal & Analysis'!G10 -> 0.056085573 | H15: ='Ratios Cal & Analysis'!H10 -> 0.052625716 | I15: ='Ratios Cal & Analysis'!I10 -> 0.038165118 | J15: ='Ratios Cal & Analysis'!J10 -> 0.03939306 | ... N15: ='Ratios Cal & Analysis'!N10 -> 0.052643648

Sheet Liquidity & Solvency Analysis
A1: Company Overview
A2: Company: Infosys Ltd
A3: Industry: IT Services
A4: Period Analysed: Mar-2014 to Mar-2025
A5: Objective: To evaluate profitability, efficiency, liquidity and capital structure using ratio analysis.
A6: Data Source: Audited Profit & Loss Account, Balance Sheet and Cash Flow Statements.
A9: Liquidity & Solvency Analysis
A11: No. | B11: Particular | C11: ='Ratios Cal & Analysis'!C3 -> 41699 | D11: ='Ratios Cal & Analysis'!D3 -> 42064 | E11: ='Ratios Cal & Analysis'!E3 -> 42430 | F11: ='Ratios Cal & Analysis'!F3 -> 42795 | G11: ='Ratios Cal & Analysis'!G3 -> 43160 | H11: ='Ratios Cal & Analysis'!H3 -> 43525 | I11: ='Ratios Cal & Analysis'!I3 -> 43891 | J11: ='Ratios Cal & Analysis'!J3 -> 44256 | ... N11: ='Ratios Cal & Analysis'!N3 -> 45717
A12: 1 | B12: Net Working Capital | C12: ='Ratios Cal & Analysis'!C11 -> 55386 | D12: ='Ratios Cal & Analysis'!D11 -> 67170 | E12: ='Ratios Cal & Analysis'!E11 -> 71442 | F12: ='Ratios Cal & Analysis'!F11 -> 64613 | G12: ='Ratios Cal & Analysis'!G11 -> 66043 | H12: ='Ratios Cal & Analysis'!H11 -> 71457 | I12: ='Ratios Cal & Analysis'!I11 -> 73884 | J12: ='Ratios Cal & Analysis'!J11 -> 86993 | ... N12: ='Ratios Cal & Analysis'!N11 -> 49114
A13: 2 | B13: Debt to Capital | C13: ='Ratios Cal & Analysis'!C15 -> 0 | D13: ='Ratios Cal & Analysis'!D15 -> 0 | E13: ='Ratios Cal & Analysis'!E15 -> 0 | F13: ='Ratios Cal & Analysis'!F15 -> 0 | G13: ='Ratios Cal & Analysis'!G15 -> 0 | H13: ='Ratios Cal & Analysis'!H15 -> 0 | I13: ='Ratios Cal & Analysis'!I15 -> 0.06610733 | J13: ='Ratios Cal & Analysis'!J15 -> 0.065196631 | ... N13: ='Ratios Cal & Analysis'!N15 -> 0.079071556

Sheet Investment & Financial Conclusi
A2: Company Overview
A3: Company: Infosys Ltd
A4: Industry: IT Services
A5: Period Analysed: Mar-2014 to Mar-2025
A6: Objective: To evaluate profitability, efficiency, liquidity and capital structure using ratio analysis.
A7: Data Source: Audited Profit & Loss Account, Balance Sheet and Cash Flow Statements.
